Metadata-Version: 2.1
Name: wtoolzexceptions
Version: 0.1.0
Summary: wtoolzexceptions contains core exception logic for web applications.
Home-page: https://github.com/e-k-m/wtoolzexceptions
Author: Eric Matti
License: UNKNOWN
Keywords: wtoolzexceptions
Platform: UNKNOWN
Classifier: Development Status :: 3 - Alpha
Classifier: Intended Audience :: Developers
Classifier: Natural Language :: English
Classifier: Programming Language :: Python :: 3
Classifier: Programming Language :: Python :: 3.6
Classifier: Programming Language :: Python :: 3.7
Classifier: Programming Language :: Python :: 3.8
Classifier: Programming Language :: Python :: 3.9
Requires-Python: >=3.6
